<?xml version="1.0" encoding="UTF-8"?>

<nrml xmlns="http://openquake.org/xmlns/nrml/0.4" xmlns:gml="http://www.opengis.net/gml">
   <sourceModel name="Source_model_1_22-Jan-2021">
<simpleFaultSource id="63" name="ModelMultiFaultsTest_Rieti_3" tectonicRegion="Active_Shallow_Crust">
     <simpleFaultGeometry>
       <gml:LineString>
       <gml:posList>
       12.9257      42.4289
       12.9389      42.4064
       12.9497      42.4047
       12.9747        42.38
       </gml:posList>
       </gml:LineString>
       <dip>55</dip>
       <upperSeismoDepth>0</upperSeismoDepth>
       <lowerSeismoDepth>10</lowerSeismoDepth>
     </simpleFaultGeometry>
       <rake>-90</rake>
       <magScaleRel>WC1994</magScaleRel>
       <ruptAspectRatio>1.0</ruptAspectRatio>
       <incrementalMFD minMag="5" binWidth="0.1">
         <occurRates> 0.0 0.0 0.0 6.911043378310906e-05 0.0 0.0 0.0 5.786585363184413e-06 4.096588713845374e-06 5.8003254206448645e-06 2.053157964800848e-06 0.0 0.0 0.0 0.0 0.0 0.0 0.0 0.0 0.0 0.0</occurRates>
       </incrementalMFD>
</simpleFaultSource>
   </sourceModel>
   </nrml>