<?xml version="1.0" encoding="UTF-8"?>

<nrml xmlns="http://openquake.org/xmlns/nrml/0.4" xmlns:gml="http://www.opengis.net/gml">
   <sourceModel name="20200520">
<characteristicFaultSource id="147" name="ModelMultiFaultsTest_scenario_f_1=['Maiella_2']_f_2=['Maiella_3']" tectonicRegion="Active_Shallow_Crust">
     <surface>
     <simpleFaultGeometry>
       <gml:LineString>
       <gml:posList>
       14.0729       42.068
       14.0802      41.9936
       </gml:posList>
       </gml:LineString>
       <dip>53</dip>
       <upperSeismoDepth>0</upperSeismoDepth>
       <lowerSeismoDepth>10</lowerSeismoDepth>
     </simpleFaultGeometry>
     <simpleFaultGeometry>
       <gml:LineString>
       <gml:posList>
       14.0802      41.9936
       14.1019      41.9245
       </gml:posList>
       </gml:LineString>
       <dip>53</dip>
       <upperSeismoDepth>0</upperSeismoDepth>
       <lowerSeismoDepth>10</lowerSeismoDepth>
     </simpleFaultGeometry>
     </surface>
       <rake>-90</rake>
       <magScaleRel>WC1994</magScaleRel>
       <ruptAspectRatio>1.0</ruptAspectRatio>
       <incrementalMFD minMag="5" binWidth="0.1">
         <occurRates> 0.0 0.0 0.0 0.0 0.0 0.0 0.0 0.0 0.0 0.0 1.930529210187866e-05 2.0500650239744156e-05 4.837782971453528e-06 1.7124440302029527e-05 7.273905193055685e-06 1.7165101724778933e-06 0.0 1.7205859696745458e-06 3.0452039597539814e-06 8.623357223590749e-07 6.104869393679594e-07</occurRates>
       </incrementalMFD>
</characteristicFaultSource>
   </sourceModel>
   </nrml>