<?xml version="1.0" encoding="UTF-8"?>

<nrml xmlns="http://openquake.org/xmlns/nrml/0.4" xmlns:gml="http://www.opengis.net/gml">
   <sourceModel name="20200520">
<characteristicFaultSource id="802" name="ModelMultiFaultsTest_scenario_f_1=['CerchioPescinaParasano_1']_f_2=['CerchioPescinaParasano_2']_f_3=['FucinoOvindoliPezza_2']_f_4=['FucinoOvindoliPezza_3']_f_5=['FucinoOvindoliPezza_4']_f_6=['Magnola_1']" tectonicRegion="Active_Shallow_Crust">
     <surface>
     <simpleFaultGeometry>
       <gml:LineString>
       <gml:posList>
       13.5562       42.067
       13.6215      42.0454
       </gml:posList>
       </gml:LineString>
       <dip>55</dip>
       <upperSeismoDepth>0</upperSeismoDepth>
       <lowerSeismoDepth>10</lowerSeismoDepth>
     </simpleFaultGeometry>
     <simpleFaultGeometry>
       <gml:LineString>
       <gml:posList>
       13.6215      42.0454
       13.6754      42.0115
       </gml:posList>
       </gml:LineString>
       <dip>55</dip>
       <upperSeismoDepth>0</upperSeismoDepth>
       <lowerSeismoDepth>10</lowerSeismoDepth>
     </simpleFaultGeometry>
     <simpleFaultGeometry>
       <gml:LineString>
       <gml:posList>
       13.5068      42.1404
       13.5609      42.0598
       </gml:posList>
       </gml:LineString>
       <dip>55</dip>
       <upperSeismoDepth>0</upperSeismoDepth>
       <lowerSeismoDepth>10</lowerSeismoDepth>
     </simpleFaultGeometry>
     <simpleFaultGeometry>
       <gml:LineString>
       <gml:posList>
       13.5609      42.0598
       13.6374      41.9897
       </gml:posList>
       </gml:LineString>
       <dip>55</dip>
       <upperSeismoDepth>0</upperSeismoDepth>
       <lowerSeismoDepth>10</lowerSeismoDepth>
     </simpleFaultGeometry>
     <simpleFaultGeometry>
       <gml:LineString>
       <gml:posList>
       13.6374      41.9897
       13.7317      41.9377
       </gml:posList>
       </gml:LineString>
       <dip>55</dip>
       <upperSeismoDepth>0</upperSeismoDepth>
       <lowerSeismoDepth>10</lowerSeismoDepth>
     </simpleFaultGeometry>
     <simpleFaultGeometry>
       <gml:LineString>
       <gml:posList>
       13.4003      42.1317
       13.4738      42.1131
       13.4915      42.1146
       13.5091      42.1021
       </gml:posList>
       </gml:LineString>
       <dip>55</dip>
       <upperSeismoDepth>0</upperSeismoDepth>
       <lowerSeismoDepth>10</lowerSeismoDepth>
     </simpleFaultGeometry>
     </surface>
       <rake>-90</rake>
       <magScaleRel>WC1994</magScaleRel>
       <ruptAspectRatio>1.0</ruptAspectRatio>
       <incrementalMFD minMag="5" binWidth="0.1">
         <occurRates> 0.0 0.0 0.0 0.0 0.0 0.0 0.0 0.0 0.0 0.0 0.0 0.0 0.0 0.0 0.0 0.0 0.0 0.0 5.6542380402760615e-06 0.0 0.0</occurRates>
       </incrementalMFD>
</characteristicFaultSource>
   </sourceModel>
   </nrml>