<?xml version="1.0" encoding="UTF-8"?>

<nrml xmlns="http://openquake.org/xmlns/nrml/0.4" xmlns:gml="http://www.opengis.net/gml">
   <sourceModel name="20200520">
<characteristicFaultSource id="176" name="ModelMultiFaultsTest_scenario_f_1=['Trasacco_1']_f_2=['Trasacco_2']" tectonicRegion="Active_Shallow_Crust">
     <surface>
     <simpleFaultGeometry>
       <gml:LineString>
       <gml:posList>
       13.4769      42.0111
       13.545      41.9479
       </gml:posList>
       </gml:LineString>
       <dip>55</dip>
       <upperSeismoDepth>0</upperSeismoDepth>
       <lowerSeismoDepth>10</lowerSeismoDepth>
     </simpleFaultGeometry>
     <simpleFaultGeometry>
       <gml:LineString>
       <gml:posList>
       13.545      41.9479
       13.5953      41.8946
       13.6123      41.8888
       </gml:posList>
       </gml:LineString>
       <dip>55</dip>
       <upperSeismoDepth>0</upperSeismoDepth>
       <lowerSeismoDepth>10</lowerSeismoDepth>
     </simpleFaultGeometry>
     </surface>
       <rake>-90</rake>
       <magScaleRel>WC1994</magScaleRel>
       <ruptAspectRatio>1.0</ruptAspectRatio>
       <incrementalMFD minMag="5" binWidth="0.1">
         <occurRates> 0.0 0.0 0.0 0.0 0.0 0.0 0.0 0.0 0.0 0.0 0.0 4.394769644961091e-05 6.22251728697918e-05 4.4052048815743444e-05 3.118646225258941e-05 1.1039162240787903e-05 1.302521395249729e-06 9.221145308371942e-06 2.611228379302204e-06 1.8486081231911958e-06 1.963071491687226e-06</occurRates>
       </incrementalMFD>
</characteristicFaultSource>
   </sourceModel>
   </nrml>