<?xml version="1.0" encoding="UTF-8"?>

<nrml xmlns="http://openquake.org/xmlns/nrml/0.4" xmlns:gml="http://www.opengis.net/gml">
   <sourceModel name="20200520">
<characteristicFaultSource id="380" name="ModelMultiFaultsTest_scenario_f_1=['CinqueMigliaAremogna_1']_f_2=['CinqueMigliaAremogna_2']_f_3=['Scanno_2']_f_4=['Scanno_3']" tectonicRegion="Active_Shallow_Crust">
     <surface>
     <simpleFaultGeometry>
       <gml:LineString>
       <gml:posList>
       13.9577      41.9157
       13.9839      41.8945
       14.0111      41.8866
       </gml:posList>
       </gml:LineString>
       <dip>54</dip>
       <upperSeismoDepth>0</upperSeismoDepth>
       <lowerSeismoDepth>10</lowerSeismoDepth>
     </simpleFaultGeometry>
     <simpleFaultGeometry>
       <gml:LineString>
       <gml:posList>
       14.0111      41.8866
       14.0254      41.8689
       14.0467      41.8658
       14.0492      41.8512
       </gml:posList>
       </gml:LineString>
       <dip>54</dip>
       <upperSeismoDepth>0</upperSeismoDepth>
       <lowerSeismoDepth>10</lowerSeismoDepth>
     </simpleFaultGeometry>
     <simpleFaultGeometry>
       <gml:LineString>
       <gml:posList>
       13.7995      42.0428
       13.8332      41.9785
       13.8555      41.9552
       </gml:posList>
       </gml:LineString>
       <dip>52</dip>
       <upperSeismoDepth>0</upperSeismoDepth>
       <lowerSeismoDepth>10</lowerSeismoDepth>
     </simpleFaultGeometry>
     <simpleFaultGeometry>
       <gml:LineString>
       <gml:posList>
       13.8555      41.9552
       13.9349      41.8831
       </gml:posList>
       </gml:LineString>
       <dip>52</dip>
       <upperSeismoDepth>0</upperSeismoDepth>
       <lowerSeismoDepth>10</lowerSeismoDepth>
     </simpleFaultGeometry>
     </surface>
       <rake>-90</rake>
       <magScaleRel>WC1994</magScaleRel>
       <ruptAspectRatio>1.0</ruptAspectRatio>
       <incrementalMFD minMag="5" binWidth="0.1">
         <occurRates> 0.0 0.0 0.0 0.0 0.0 0.0 0.0 0.0 0.0 0.0 0.0 0.0 0.0 0.0 0.0 0.0 4.911543694551687e-06 1.0431319960129115e-05 1.2308014985559236e-05 3.4853629292653392e-06 4.93489598564431e-06</occurRates>
       </incrementalMFD>
</characteristicFaultSource>
   </sourceModel>
   </nrml>